osbeautify/__init__.py
osbeautify-1.4.dist-info/METADATA
osbeautify-1.4.dist-info/WHEEL
osbeautify-1.4.dist-info/top_level.txt
osbeautify-1.4.dist-info/RECORD
