Metadata-Version: 2.1
Name: osbeautify
Version: 1.4
Summary: python3 package to colors your output
Author-email: rootosdev@gmail.com
License: Eclipse Public License 2.0
